{
  "$schema": "https://mintlify.com/docs.json",
  "theme": "maple",
  "name": "WPQ Project Execution Repository",
  "colors": {
    "primary": "#374151",
    "light": "#9CA3AF",
    "dark": "#374151"
  },
  "fonts": {
    "family": "Inter"
  },
  "logo": {
    "light": "/logo/westpaq-logo-horizontal-light.png",
    "dark": "/logo/westpaq-logo-horizontal-dark.png"
  },
  "favicon": "/logo/westpaq-favicon-512.png",
  "navigation": {
    "groups": [
      {
        "group": "Overview",
        "pages": ["index"]
      },
      {
        "group": "Service Line Modules",
        "pages": [
          "service-lines/engineering-and-design",
          "service-lines/installations",
          "service-lines/inspections",
          "service-lines/maintenance"
        ]
      },
      {
        "group": "Archive",
        "pages": ["past-project-records"]
      }
    ]
  }
}
